{"index":{"links":{"/":[{"source":"/","target":"/notes/gardening/Gardeners-Guide","text":"Gardeners Guide"},{"source":"/","target":"/notes/bookclub","text":"Book Club"},{"source":"/","target":"/notes/zine","text":"Zines"},{"source":"/","target":"/notes/rituals","text":"Rituals of the Garden"},{"source":"/","target":"/notes/sessions","text":"Gradening Sessions"},{"source":"/","target":"/notes/bfgf","text":"A list of descriptions"},{"source":"/","target":"/content/notes/grimoire","text":"The Grimoire"}],"/.trash/Bookclub":[{"source":"/.trash/Bookclub","target":"/notes/bookclub/toad","text":"The Common Toad, George Orwel"},{"source":"/.trash/Bookclub","target":"/notes/bookclub/toad_brin","text":"Brin's Notes"},{"source":"/.trash/Bookclub","target":"/notes/bookclub/toad_jen","text":"Jen's Notes"}],"/notes/bookclub":[{"source":"/notes/bookclub","target":"/notes/bookclub/Brin-on-Toad","text":"Brin’s Notes"},{"source":"/notes/bookclub","target":"/notes/bookclub/Jen-on-WHTRTP","text":"Jen's Notes"}],"/notes/bookclub/Brin-on-Toad":[{"source":"/notes/bookclub/Brin-on-Toad","target":"/","text":""}],"/notes/grimoire":[{"source":"/notes/grimoire","target":"/content/notes/grimoire/przganka","text":"Przganka"}],"/notes/rituals":[{"source":"/notes/rituals","target":"/notes/rituals/Summoning-a-Frog","text":"Summoning a Frog"}],"/notes/sessions":[{"source":"/notes/sessions","target":"/notes/sessions/august_haag","text":"3-6 of August, Haag"}],"/notes/sessions/august_haag":[{"source":"/notes/sessions/august_haag","target":"/content/notes/bookclub","text":"Bookclub date"}],"/notes/zine":[{"source":"/notes/zine","target":"/notes/zine/how2zine","text":"how to make zines"}]},"backlinks":{"/":[{"source":"/notes/bookclub/Brin-on-Toad","target":"/","text":""}],"/content/notes/bookclub":[{"source":"/notes/sessions/august_haag","target":"/content/notes/bookclub","text":"Bookclub date"}],"/content/notes/grimoire":[{"source":"/","target":"/content/notes/grimoire","text":"The Grimoire"}],"/content/notes/grimoire/przganka":[{"source":"/notes/grimoire","target":"/content/notes/grimoire/przganka","text":"Przganka"}],"/notes/bfgf":[{"source":"/","target":"/notes/bfgf","text":"A list of descriptions"}],"/notes/bookclub":[{"source":"/","target":"/notes/bookclub","text":"Book Club"}],"/notes/bookclub/Brin-on-Toad":[{"source":"/notes/bookclub","target":"/notes/bookclub/Brin-on-Toad","text":"Brin’s Notes"}],"/notes/bookclub/Jen-on-WHTRTP":[{"source":"/notes/bookclub","target":"/notes/bookclub/Jen-on-WHTRTP","text":"Jen's Notes"}],"/notes/bookclub/toad":[{"source":"/.trash/Bookclub","target":"/notes/bookclub/toad","text":"The Common Toad, George Orwel"}],"/notes/bookclub/toad_brin":[{"source":"/.trash/Bookclub","target":"/notes/bookclub/toad_brin","text":"Brin's Notes"}],"/notes/bookclub/toad_jen":[{"source":"/.trash/Bookclub","target":"/notes/bookclub/toad_jen","text":"Jen's Notes"}],"/notes/gardening/Gardeners-Guide":[{"source":"/","target":"/notes/gardening/Gardeners-Guide","text":"Gardeners Guide"}],"/notes/rituals":[{"source":"/","target":"/notes/rituals","text":"Rituals of the Garden"}],"/notes/rituals/Summoning-a-Frog":[{"source":"/notes/rituals","target":"/notes/rituals/Summoning-a-Frog","text":"Summoning a Frog"}],"/notes/sessions":[{"source":"/","target":"/notes/sessions","text":"Gradening Sessions"}],"/notes/sessions/august_haag":[{"source":"/notes/sessions","target":"/notes/sessions/august_haag","text":"3-6 of August, Haag"}],"/notes/zine":[{"source":"/","target":"/notes/zine","text":"Zines"}],"/notes/zine/how2zine":[{"source":"/notes/zine","target":"/notes/zine/how2zine","text":"how to make zines"}]}},"links":[{"source":"/.trash/Bookclub","target":"/notes/bookclub/toad","text":"The Common Toad, George Orwel"},{"source":"/.trash/Bookclub","target":"/notes/bookclub/toad_brin","text":"Brin's Notes"},{"source":"/.trash/Bookclub","target":"/notes/bookclub/toad_jen","text":"Jen's Notes"},{"source":"/","target":"/notes/gardening/Gardeners-Guide","text":"Gardeners Guide"},{"source":"/","target":"/notes/bookclub","text":"Book Club"},{"source":"/","target":"/notes/zine","text":"Zines"},{"source":"/","target":"/notes/rituals","text":"Rituals of the Garden"},{"source":"/","target":"/notes/sessions","text":"Gradening Sessions"},{"source":"/","target":"/notes/bfgf","text":"A list of descriptions"},{"source":"/","target":"/content/notes/grimoire","text":"The Grimoire"},{"source":"/notes/bookclub/Brin-on-Toad","target":"/","text":""},{"source":"/notes/bookclub","target":"/notes/bookclub/Brin-on-Toad","text":"Brin’s Notes"},{"source":"/notes/bookclub","target":"/notes/bookclub/Jen-on-WHTRTP","text":"Jen's Notes"},{"source":"/notes/grimoire","target":"/content/notes/grimoire/przganka","text":"Przganka"},{"source":"/notes/rituals","target":"/notes/rituals/Summoning-a-Frog","text":"Summoning a Frog"},{"source":"/notes/sessions/august_haag","target":"/content/notes/bookclub","text":"Bookclub date"},{"source":"/notes/sessions","target":"/notes/sessions/august_haag","text":"3-6 of August, Haag"},{"source":"/notes/zine","target":"/notes/zine/how2zine","text":"how to make zines"}]}